tests/__init__.py
tests/test_calc.py
tks_api_official/__init__.py
tks_api_official/calc.py
tks_api_official-1.0.3.dist-info/LICENSE
tks_api_official-1.0.3.dist-info/METADATA
tks_api_official-1.0.3.dist-info/WHEEL
tks_api_official-1.0.3.dist-info/top_level.txt
tks_api_official-1.0.3.dist-info/RECORD
