Metadata-Version: 2.1
Name: tks-api-official
Version: 1.0.3
Summary: A powerful customs calculation API for vehicles with currency conversion.
Home-page: https://github.com/markolofsen/tks-api
Author: Unrealos.com
Author-email: m@unrealos.com
Project-URL: Bug Tracker, https://github.com/markolofsen/tks-api/issues
Classifier: Programming Language :: Python :: 3
Classifier: License :: OSI Approved :: MIT License
Classifier: Operating System :: OS Independent
Classifier: Topic :: Software Development :: Libraries :: Application Frameworks
Requires-Python: >=3.7
License-File: LICENSE
Requires-Dist: requests
Requires-Dist: pyyaml
Requires-Dist: tabulate
Requires-Dist: currency-converter-free
Provides-Extra: dev
Requires-Dist: pytest; extra == "dev"
Requires-Dist: unittest; extra == "dev"
Requires-Dist: black; extra == "dev"
Requires-Dist: flake8; extra == "dev"
Requires-Dist: isort; extra == "dev"
